deep_decoder/__init__.py
deep_decoder/decoder.py
deep_decoder-1.0.2.dist-info/licenses/LICENSE
deep_decoder-1.0.2.dist-info/METADATA
deep_decoder-1.0.2.dist-info/WHEEL
deep_decoder-1.0.2.dist-info/top_level.txt
deep_decoder-1.0.2.dist-info/RECORD
