Metadata-Version: 2.4
Name: deep-decoder
Version: 1.0.2
Summary: Deep Decoder for IDS/IPS, WAF - A comprehensive multi-layer encoding/decoding library for security analysis
Home-page: https://github.com/khoilv2005/deep-decoder
Author: khoilv2005
Author-email: khoilv2005 <khoilv2005@example.com>
License: MIT
Project-URL: Homepage, https://github.com/khoilv2005/deep-decoder
Project-URL: Bug Reports, https://github.com/khoilv2005/deep-decoder/issues
Project-URL: Source, https://github.com/khoilv2005/deep-decoder
Keywords: decoder,encoder,base64,url,hex,html,encoding,decoding,security,ids,ips,waf
Classifier: Development Status :: 4 - Beta
Classifier: Intended Audience :: Developers
Classifier: Topic :: Software Development :: Libraries :: Python Modules
Classifier: Topic :: Security
Classifier: Topic :: Text Processing
Classifier: License :: OSI Approved :: MIT License
Classifier: Programming Language :: Python :: 3
Classifier: Programming Language :: Python :: 3.7
Classifier: Programming Language :: Python :: 3.8
Classifier: Programming Language :: Python :: 3.9
Classifier: Programming Language :: Python :: 3.10
Classifier: Programming Language :: Python :: 3.11
Classifier: Programming Language :: Python :: 3.12
Requires-Python: >=3.7
License-File: LICENSE
Provides-Extra: dev
Requires-Dist: pytest>=7.0; extra == "dev"
Requires-Dist: pytest-cov>=4.0; extra == "dev"
Requires-Dist: black>=22.0; extra == "dev"
Requires-Dist: flake8>=5.0; extra == "dev"
Requires-Dist: mypy>=0.990; extra == "dev"
Dynamic: author
Dynamic: home-page
Dynamic: license-file
Dynamic: requires-python
